{"cameraMode":{"drawMode":0,"name":"Shaded","section":"Shading Mode"},"sceneLighting":true,"audioPlay":false,"sceneViewState":{"m_AlwaysRefresh":false,"showFog":true,"showSkybox":true,"showFlares":true,"showImageEffects":true,"showParticleSystems":true,"showVisualEffectGraphs":true,"m_FxEnabled":true},"in2DMode":false,"pivot":{"x":5.928340911865234,"y":0.5434679985046387,"z":-2.714942455291748},"rotation":{"x":0.11797194927930832,"y":0.6674060225486755,"z":-0.10825996845960617,"w":0.727278470993042},"size":10.0,"orthographic":false}